[
  {
    "nom": "MOREL",
    "prenom": "Valérie",
    "telephone": "04 92 72 06 20",
    "etablissement": "CLG GIONO 04",
    "departement": "4",
    "secteur": "PU",
    "ville": "MANOSQUE",
    "mailAcademique": "valerie.morel@ac-aix-marseille.fr",
    "mailFonctionnel": "directeur.segpa.giono04@ac-aix-marseille.fr"
  },
  {
    "nom": "KERN",
    "prenom": "Anne",
    "telephone": "04 91 21 50 30",
    "etablissement": "CLG EDOUARD MANET",
    "departement": "13",
    "secteur": "PU",
    "ville": "MARSEILLE",
    "mailAcademique": "anne.kern@ac-aix-marseille.fr",
    "mailFonctionnel": "directeur.segpa.manet@ac-aix-marseille.fr"
  },
  {
    "nom": "KALUZNY",
    "prenom": "François",
    "telephone": "04 91 09 54 33",
    "etablissement": "CLG ARTHUR RIMBAUD",
    "departement": "13",
    "secteur": "PU",
    "ville": "MARSEILLE",
    "mailAcademique": "francois.kaluzny@ac-aix-marseille.fr",
    "mailFonctionnel": "directeur.segpa.rimbaud@ac-aix-marseille.fr"
  },
  {
    "nom": "GARCIA",
    "prenom": "Corinne",
    "telephone": "04 42 36 95 00",
    "etablissement": "CLG LOU GARLABAN",
    "departement": "13",
    "secteur": "PU",
    "ville": "AUBAGNE",
    "mailAcademique": "corinne.garcia-leonetti@ac-aix-marseille.fr",
    "mailFonctionnel": "ce.0132412b@ac-aix-marseille.fr"
  },
  {
    "nom": "DAVIN",
    "prenom": "Delphine",
    "telephone": "04 92 51 29 64",
    "etablissement": "CLG FONTREYNE",
    "departement": "5",
    "secteur": "PU",
    "ville": "GAP",
    "mailAcademique": "c.0050480v@ac-aix-marseille.fr",
    "mailFonctionnel": "directeur.segpa.fontreyne@ac-aix-marseille.fr"
  },
  {
    "nom": "THUEUX",
    "prenom": "Séverine",
    "telephone": "04 90 53 16 43",
    "etablissement": "CLG JOSEPH D'ARBAUD",
    "departement": "13",
    "secteur": "PU",
    "ville": "SALON",
    "mailAcademique": "severine.thueux@ac-aix-marseille.fr",
    "mailFonctionnel": "directeur.segpa.darbaud13@ac-aix-marseille.fr"
  },
  {
    "nom": "CAPECCHI",
    "prenom": "Céline",
    "telephone": "04 92 32 19 05",
    "etablissement": "CLG GASSENDI",
    "departement": "4",
    "secteur": "PU",
    "ville": "DIGNE-LES-BAINS",
    "mailAcademique": "celine.labat@ac-aix-marseille.fr",
    "mailFonctionnel": "directeur.segpa.digne@ac-aix-marseille.fr"
  },
  {
    "nom": "CARON",
    "prenom": "Pierre",
    "telephone": "04 90 63 04 41",
    "etablissement": "CLG RASPAIL",
    "departement": "84",
    "secteur": "PU",
    "ville": "CARPENTRAS",
    "mailAcademique": "pierre.caron@ac-aix-marseille.fr",
    "mailFonctionnel": "directeur.segpa.raspail@ac-aix-marseille.fr"
  },
  {
    "nom": "LE GOUPIL",
    "prenom": "Cendrine",
    "telephone": "04 42 80 18 99",
    "etablissement": "CLG MARCEL PAGNOL",
    "departement": "13",
    "secteur": "PU",
    "ville": "MARTIGUES",
    "mailAcademique": null,
    "mailFonctionnel": "directeur.segpa.pagnol13@ac-aix-marseille.fr"
  },
  {
    "nom": "LE GOUPIL",
    "prenom": "Cendrine",
    "telephone": "04 42 06 25 08",
    "etablissement": "CLG FREDERIC MISTRAL",
    "departement": "13",
    "secteur": "PU",
    "ville": "PORT-DE-BOUC",
    "mailAcademique": "cendrine.le-goupil@ac-aix-marseille.fr",
    "mailFonctionnel": "ce.0132212j@ac-aix-marseille.fr"
  },
  {
    "nom": "COPIN",
    "prenom": "Véronique",
    "telephone": "04 90 51 28 00",
    "etablissement": "CLG GIONO",
    "departement": "84",
    "secteur": "PU",
    "ville": "ORANGE",
    "mailAcademique": "veronique.copin@ac-aix-marseille.fr",
    "mailFonctionnel": "ce.0840116v@ac-aix-marseille.fr"
  },
  {
    "nom": "DELPORTE",
    "prenom": "Jean-Denis",
    "telephone": "04 90 71 15 96",
    "etablissement": "CLG GAUTHIER",
    "departement": "84",
    "secteur": "PU",
    "ville": "CAVAILLON",
    "mailAcademique": "jean-denis.delporte@ac-aix-marseille.fr",
    "mailFonctionnel": "ce.0840018n@ac-aix-marseille.fr"
  },
  {
    "nom": "DUCLOS",
    "prenom": "Florence",
    "telephone": "04 90 87 42 16",
    "etablissement": "CLG ANSELME MATHIEU LE LAVARIN ANN",
    "departement": "84",
    "secteur": "PU",
    "ville": "AVIGNON",
    "mailAcademique": "Florence.Duclos@ac-aix-marseille.fr",
    "mailFonctionnel": "ce.0840108L@ac-aix-marseille.fr"
  },
  {
    "nom": "VIART",
    "prenom": "Céline",
    "telephone": "04 91 09 27 01",
    "etablissement": "CLG BARNIER",
    "departement": "13",
    "secteur": "PU",
    "ville": "MARSEILLE",
    "mailAcademique": "celine.viard3@ac-aix-marseille.fr",
    "mailFonctionnel": "ce.0130073j@ac-aix-marseille.fr"
  },
  {
    "nom": "LE BRIS",
    "prenom": "Hélène",
    "telephone": "04 92 53 58 57",
    "etablissement": "CLG MAUZAN",
    "departement": "5",
    "secteur": "PU",
    "ville": "GAP",
    "mailAcademique": "helene.le-bris@ac-aix-marseille.fr",
    "mailFonctionnel": "ce.0050025A@ac-aix-marseille.fr"
  },
  {
    "nom": "DELENAT",
    "prenom": "Fabienne",
    "telephone": "04 42 77 57 20",
    "etablissement": "CLG HENRI BOSCO",
    "departement": "13",
    "secteur": "PU",
    "ville": "VITROLLES",
    "mailAcademique": "fabienne.delenat@ac-aix-marseille.fr",
    "mailFonctionnel": "directeur.segpa.bosco@ac-aix-marseille.fr"
  },
  {
    "nom": "HAMON",
    "prenom": "Isabelle",
    "telephone": "04 42 88 49 10",
    "etablissement": "CLG EMILIE DE MIRABEAU",
    "departement": "13",
    "secteur": "PU",
    "ville": "MARIGNANE",
    "mailAcademique": "isabelle.hamon@ac-aix-marseille.fr",
    "mailFonctionnel": "ce.0131608c@ac-aix-marseille.fr"
  },
  {
    "nom": "MARION",
    "prenom": "Patrice",
    "telephone": "04 42 85 40 76",
    "etablissement": "CLG FERDINAND LEGER",
    "departement": "13",
    "secteur": "PU",
    "ville": "BERRE-L'ÉTANG",
    "mailAcademique": "patrice.marion@ac-aix-marseille.fr",
    "mailFonctionnel": "directeur.segpa.leger@ac-aix-marseille.fr"
  },
  {
    "nom": "MASSA",
    "prenom": "Stéphanie",
    "telephone": "04 91 62 58 71",
    "etablissement": "CLG ALEXANDRE DUMAS",
    "departement": "13",
    "secteur": "PU",
    "ville": "MARSEILLE",
    "mailAcademique": "stephanie.massa@ac-aix-marseille.fr",
    "mailFonctionnel": "segpadumas@gmail.com"
  },
  {
    "nom": "RESSAYRE",
    "prenom": "Audrey",
    "telephone": "04 42 56 14 27",
    "etablissement": "CLG ALPHONSE DAUDET",
    "departement": "13",
    "secteur": "PU",
    "ville": "ISTRES",
    "mailAcademique": "audrey.ressayre@ac-aix-marseille.fr",
    "mailFonctionnel": "directeur.segpa.daudet13@ac-aix-marseille.fr"
  },
  {
    "nom": "CARMONA",
    "prenom": "Vincent",
    "telephone": "04 91 37 48 86",
    "etablissement": "ST VINCENT DE PAUL (CE)",
    "departement": "13",
    "secteur": "PR",
    "ville": "MARSEILLE",
    "mailAcademique": "vincent.carmona@ac-aix-marseille.fr",
    "mailFonctionnel": "ce.0133702d@ac-aix-marseille.fr"
  },
  {
    "nom": "BAILLIU",
    "prenom": "Stéphanie",
    "telephone": "04 42 27 73 89",
    "etablissement": "CLG ARC DE MEYRAN",
    "departement": "13",
    "secteur": "PU",
    "ville": "AIX",
    "mailAcademique": "stephanie.bailliu@ac-aix-marseille.fr",
    "mailFonctionnel": "directeur.segpa.arcdemeyran@ac-aix-marseille.fr"
  },
  {
    "nom": "PERONA",
    "prenom": "Serge",
    "telephone": "04 90 91 09 64",
    "etablissement": "CLG RENÉ CASSIN",
    "departement": "13",
    "secteur": "PU",
    "ville": "TARASCON",
    "mailAcademique": "serge.perona@ac-aix-marseille.fr",
    "mailFonctionnel": "directeur.segpa.cassin13@ac-aix-marseille.fr"
  },
  {
    "nom": "PRATO",
    "prenom": "Laurent",
    "telephone": "04 92 21 29 24",
    "etablissement": "CLG GARCINS",
    "departement": "5",
    "secteur": "PU",
    "ville": "BRIANÇON",
    "mailAcademique": "laurent.prato@ac-aix-marseille.fr",
    "mailFonctionnel": "directeur.segpa.garcins@ac-aix-marseille.fr"
  },
  {
    "nom": "QUENEHEN",
    "prenom": "Denis",
    "telephone": "04 90 30 56 48",
    "etablissement": "CLG HENRI BOUDON",
    "departement": "84",
    "secteur": "PU",
    "ville": "BOLLÈNE",
    "mailAcademique": "denis.quenehen@ac-aix-marseille.fr",
    "mailFonctionnel": "ce.0840437u@ac-aix-marseille.fr"
  },
  {
    "nom": "RAIMONDO",
    "prenom": "Pierre",
    "telephone": "04 42 98 10 40",
    "etablissement": "CLG LES MATAGOTS",
    "departement": "13",
    "secteur": "PU",
    "ville": "LA CIOTAT",
    "mailAcademique": "pierre.raimondo@ac-aix-marseille.fr",
    "mailFonctionnel": "directeur.segpa.matagots@ac-aix-marseille.fr"
  },
  {
    "nom": "REANT",
    "prenom": "Laëtitia",
    "telephone": "04 90 31 50 00",
    "etablissement": "CLG JULES VERNE",
    "departement": "84",
    "secteur": "PU",
    "ville": "LE PONTET",
    "mailAcademique": "laetitia.reant@ac-aix-marseille.fr",
    "mailFonctionnel": "directeur.segpa.verne@ac-aix-marseille.fr"
  },
  {
    "nom": "REMALI",
    "prenom": "Saada",
    "telephone": "04 96 20 61 70",
    "etablissement": "CLG LOUISE MICHEL",
    "departement": "13",
    "secteur": "PU",
    "ville": "MARSEILLE",
    "mailAcademique": "saada.remali@ac-aix-marseille.fr",
    "mailFonctionnel": "ce.0134023c@ac-aix-marseille.fr"
  },
  {
    "nom": "ROUZADE",
    "prenom": "Sylvie",
    "telephone": "04 91 48 05 92",
    "etablissement": "CLG DU SACRÉ COEUR",
    "departement": "13",
    "secteur": "PR",
    "ville": "MARSEILLE",
    "mailAcademique": "sylvie.rouzade@ac-aix-marseille.fr",
    "mailFonctionnel": "ce.0132950l@ac-aix-marseille.fr"
  },
  {
    "nom": "RIPOLL",
    "prenom": "Christel",
    "telephone": "04 91 49 00 93",
    "etablissement": "CLG DARIUS MILHAUD",
    "departement": "13",
    "secteur": "PU",
    "ville": "MARSEILLE",
    "mailAcademique": "christel.ripoll@ac-aix-marseille.fr",
    "mailFonctionnel": "ce.0131756n@ac-aix-marseille.fr"
  },
  {
    "nom": "TEOULLE",
    "prenom": "Eric",
    "telephone": "04 90 09 72 27",
    "etablissement": "CLG PAGNOL",
    "departement": "84",
    "secteur": "PU",
    "ville": "PERTUIS",
    "mailAcademique": "eric.teoulle@ac-aix-marseille.fr",
    "mailFonctionnel": "directeur.segpa.pagnol84@ac-aix-marseille.fr"
  },
  {
    "nom": "RODRIGUEZ",
    "prenom": "Wladimir",
    "telephone": "04 90 73 39 70",
    "etablissement": "CLG MONT SAUVY",
    "departement": "13",
    "secteur": "PU",
    "ville": "ORGON",
    "mailAcademique": "wladimir.rodriguez@ac-aix-marseille.fr",
    "mailFonctionnel": "ce.0132217p@ac-aix-marseille.fr"
  },
  {
    "nom": "RODRIGUEZ",
    "prenom": "Wladimir",
    "telephone": "04 90 92 03 85",
    "etablissement": "CLG GLANUM",
    "departement": "13",
    "secteur": "PU",
    "ville": "ST-RÉMY-DE-PROVENCE",
    "mailAcademique": null,
    "mailFonctionnel": "ce.0132573b@ac-aix-marseille.fr"
  },
  {
    "nom": "TOUFOUTI",
    "prenom": "Said",
    "telephone": "04 91 10 00 80",
    "etablissement": "CLG JACQUES PRÉVERT",
    "departement": "13",
    "secteur": "PU",
    "ville": "MARSEILLE",
    "mailAcademique": "said.toufouti@ac-aix-marseille.fr",
    "mailFonctionnel": "directeur.segpa.prevert.marseille@ac-aix-marseille.fr"
  },
  {
    "nom": "RUIZ",
    "prenom": "Ingrid",
    "telephone": "04 91 75 42 45",
    "etablissement": "CLG MENU",
    "departement": "13",
    "secteur": "PU",
    "ville": "MARSEILLE",
    "mailAcademique": "ingrid.ruiz@ac-aix-marseille.fr",
    "mailFonctionnel": "directeur.segpa.menu@ac-aix-marseille.fr"
  },
  {
    "nom": "BORDA",
    "prenom": "Julie",
    "telephone": "04 91 87 51 51",
    "etablissement": "CLG CAILLOLS",
    "departement": "13",
    "secteur": "PU",
    "ville": "MARSEILLE",
    "mailAcademique": "julie.borda@ac-aix-marseille.fr",
    "mailFonctionnel": "ce.0131968u@ac-aix-marseille.fr"
  },
  {
    "nom": "BORDA",
    "prenom": "Julie",
    "telephone": "04 91 44 74 18",
    "etablissement": "CLG CHÂTEAU FORBIN",
    "departement": "13",
    "secteur": "PU",
    "ville": "MARSEILLE",
    "mailAcademique": null,
    "mailFonctionnel": "ce.0132401P@ac-aix-marseille.fr"
  },
  {
    "nom": "CONSTANT",
    "prenom": "Gregory",
    "telephone": "04 90 58 09 30",
    "etablissement": "CLG MIRAMARIS",
    "departement": "13",
    "secteur": "PU",
    "ville": "MIRAMAS",
    "mailAcademique": "gregory.constant@ac-aix-marseille.fr",
    "mailFonctionnel": "directeur.segpa.miramaris@ac-aix-marseille.fr"
  },
  {
    "nom": "VEGA",
    "prenom": "Bruno",
    "telephone": "04 91 09 02 02",
    "etablissement": "CLG JEAN MOULIN",
    "departement": "13",
    "secteur": "PU",
    "ville": "MARSEILLE",
    "mailAcademique": "bruno.vega@ac-aix-marseille.fr",
    "mailFonctionnel": "ce.0133779m@ac-aix-marseille.fr"
  },
  {
    "nom": "BRASSAC",
    "prenom": "Christophe",
    "telephone": "04 90 39 22 16",
    "etablissement": "CLG DIDEROT",
    "departement": "84",
    "secteur": "PU",
    "ville": "SORGUES",
    "mailAcademique": "christophe.brassac@ac-aix-marseille.fr",
    "mailFonctionnel": "directeur.segpa.diderot@ac-aix-marseille.fr"
  },
  {
    "nom": "ZARKA",
    "prenom": "Jean-Philippe",
    "telephone": "04 90 96 47 48",
    "etablissement": "CLG ROBERT MOREL",
    "departement": "13",
    "secteur": "PU",
    "ville": "ARLES",
    "mailAcademique": "jean-philippe.zarka@ac-aix-marseille.fr",
    "mailFonctionnel": "directeur.segpa.morel@ac-aix-marseille.fr"
  },
  {
    "nom": "ZAWADZKI",
    "prenom": "Dorian",
    "telephone": "04 42 52 28 00",
    "etablissement": "CLG MURIEL HURTIS",
    "departement": "13",
    "secteur": "PU",
    "ville": "AIX",
    "mailAcademique": "dorian.zawadzki@ac-aix-marseille.fr",
    "mailFonctionnel": "directeur.segpa.jasdebouffan@ac-aix-marseille.fr"
  },
  {
    "nom": "TROCME",
    "prenom": "Céline",
    "telephone": "04 91 01 55 10",
    "etablissement": "CLG IZZO",
    "departement": "13",
    "secteur": "PU",
    "ville": "MARSEILLE",
    "mailAcademique": "celine.trocme-dumesnil@ac-aix-marseille.fr",
    "mailFonctionnel": "ce0133788x@ac-aix-marseille.fr"
  },
  {
    "nom": "DELCLOS",
    "prenom": "Olivier",
    "telephone": null,
    "etablissement": "DDFPT EREA VINCENSINI",
    "departement": "84",
    "secteur": "PU",
    "ville": "VEDÈNE",
    "mailAcademique": "olivier.delclos@ac-aix-marseille.fr",
    "mailFonctionnel": "ddfpt.0840096Y@ac-aix-marseille.fr"
  },
  {
    "nom": "FAURE",
    "prenom": "Magali",
    "telephone": null,
    "etablissement": "DDFPT EREA ARAGON",
    "departement": "13",
    "secteur": "PU",
    "ville": "PENNES-MIRABEAU",
    "mailAcademique": "magali.faure@ac-aix-marseille.fr",
    "mailFonctionnel": "ddfpt.0132343B@ac-aix-marseille.fr"
  }
]